Metadata-Version: 2.1
Name: odoo8-addon-hr-department-sequence
Version: 8.0.1.0.0.99.dev21
Summary: Add sequence on department
Home-page: http://www.openerp.com
Author: Michael Telahun Makonnen <mmakonnen@gmail.com>,Odoo Community Association (OCA)
Author-email: support@odoo-community.org
License: AGPL-3
Platform: UNKNOWN
Classifier: Programming Language :: Python
Classifier: Framework :: Odoo
Classifier: License :: OSI Approved :: GNU Affero General Public License v3
Requires-Python: ~=2.7
Requires-Dist: odoo (<9.0a,>=8.0a)
